LogExportTable3.py
setup.py
LogExportTable3.egg-info/PKG-INFO
LogExportTable3.egg-info/SOURCES.txt
LogExportTable3.egg-info/dependency_links.txt
LogExportTable3.egg-info/requires.txt
LogExportTable3.egg-info/top_level.txt